mock_django/__init__.py
mock_django/http.py
mock_django/managers.py
mock_django/models.py
mock_django/query.py
mock_django/shared.py
mock_django/signals.py
mock_django-0.6.10.dist-info/DESCRIPTION.rst
mock_django-0.6.10.dist-info/METADATA
mock_django-0.6.10.dist-info/RECORD
mock_django-0.6.10.dist-info/WHEEL
mock_django-0.6.10.dist-info/metadata.json
mock_django-0.6.10.dist-info/top_level.txt
